{"cast": [{"adult": false, "backdrop_path": "/nPZueeFStMBVajT5PggC8ncb9r1.jpg", "genre_ids": [99], "id": 215332, "origin_country": ["FR"], "original_language": "fr", "original_name": "Canadiens Nordiques - La rivalit\u00e9", "overview": "", "popularity": 7.189, "poster_path": "/hRNkG4b4QQ3ZvQU1Sbt20cApnJt.jpg", "first_air_date": "2022-11-29", "name": "Canadiens Nordiques - La rivalit\u00e9", "vote_average": 0.0, "vote_count": 0, "character": "Self", "credit_id": "6386db44cb8028007cb57223", "episode_count": 1, "media_type": "tv"}, {"adult": false, "backdrop_path": "/i0nodkJcjM1lfi0CwzChkIynbop.jpg", "genre_ids": [10767], "id": 61308, "origin_country": ["CA"], "original_language": "fr", "original_name": "Les enfants de la t\u00e9l\u00e9", "overview": "", "popularity": 119.734, "poster_path": "/19ua2uWWnNjbXYay3ls2o5i3owS.jpg", "first_air_date": "2010-09-15", "name": "Les enfants de la t\u00e9l\u00e9", "vote_average": 6.5, "vote_count": 1, "character": "Self", "credit_id": "5e38e67f9824c800162791a3", "episode_count": 1, "media_type": "tv"}], "crew": [], "id": 2128705}